rstcloth/__init__.py
rstcloth/rstcloth.py
rstcloth/utils.py
rstcloth-0.6.0.dist-info/LICENSE
rstcloth-0.6.0.dist-info/METADATA
rstcloth-0.6.0.dist-info/WHEEL
rstcloth-0.6.0.dist-info/RECORD
