Metadata-Version: 2.1
Name: rstcloth
Version: 0.6.0
Summary: A simple Python API for generating RestructuredText.
Home-page: https://github.com/thclark/rstcloth
License: MIT
Keywords: sphinx,rst,restructuredtext,documentation,rest,docutils
Author: Tom Clark
Requires-Python: >=3.7,<4
Classifier: Development Status :: 4 - Beta
Classifier: Intended Audience :: Developers
Classifier: License :: OSI Approved :: MIT License
Classifier: Natural Language :: English
Classifier: Operating System :: OS Independent
Classifier: Programming Language :: Python :: 3
Classifier: Programming Language :: Python :: 3.7
Classifier: Programming Language :: Python :: 3.8
Classifier: Programming Language :: Python :: 3.9
Classifier: Programming Language :: Python :: 3.10
Classifier: Programming Language :: Python :: 3.11
Classifier: Programming Language :: Python :: 3.10
Classifier: Programming Language :: Python :: 3.11
Classifier: Programming Language :: Python :: 3.12
Classifier: Programming Language :: Python :: 3.8
Classifier: Programming Language :: Python :: 3.9
Classifier: Topic :: Documentation
Classifier: Topic :: Documentation :: Sphinx
Classifier: Topic :: Software Development :: Documentation
Classifier: Topic :: Text Processing
Classifier: Topic :: Utilities
Provides-Extra: docs
Requires-Dist: PyYAML (>=5,<7)
Requires-Dist: Pygments (>=2.12.0,<3.0.0)
Requires-Dist: sphinx (>=2,<8) ; extra == "docs"
Requires-Dist: sphinx-charts (==0.1.2) ; extra == "docs"
Requires-Dist: sphinx-rtd-theme (==1.0.0) ; extra == "docs"
Requires-Dist: sphinx-tabs (==3.2.0) ; extra == "docs"
Requires-Dist: tabulate (>=0.8.9,<0.10)
Project-URL: Repository, https://github.com/thclark/rstcloth
